face_processor/__init__.py
face_processor/_app.py
face_processor/_face_processor.py
face_processor/shape_predictor_68_face_landmarks.dat
face_processor-1.6.dist-info/entry_points.txt
face_processor-1.6.dist-info/WHEEL
face_processor-1.6.dist-info/METADATA
face_processor-1.6.dist-info/RECORD
