Metadata-Version: 2.1
Name: face_processor
Version: 1.6
Summary: Transform faces for use in RSVP experiments
Author-email: Robbert van der Mijn <robbertmijn@gmail.com>
Requires-Python: >=3.5
Classifier: License :: OSI Approved :: MIT License
Requires-Dist: opencv-python
Requires-Dist: dlib
Requires-Dist: imutils
Requires-Dist: matplotlib
Requires-Dist: numpy
Project-URL: Documentation, https://github.com/robbertmijn/face_processor
Project-URL: Source, https://github.com/robbertmijn/face_processor
